hirakord/__init__.py
hirakord/__main__.py
hirakord/templates/helpers/cog.txt
hirakord/templates/helpers/embed.txt
hirakord/templates/helpers/logger.txt
hirakord/templates/helpers/tree.txt
hirakord/templates/helpers/ui.txt
hirakord-0.0.1.dist-info/LICENSE
hirakord-0.0.1.dist-info/METADATA
hirakord-0.0.1.dist-info/WHEEL
hirakord-0.0.1.dist-info/top_level.txt
hirakord-0.0.1.dist-info/RECORD
