Metadata-Version: 2.1
Name: hirakord
Version: 0.0.1
Summary: Build bots faster with hirakord.
Home-page: https://github.com/ExHiraku/hirakord
Author: ExHiraku
License: MIT
Requires-Python: >=3.8
License-File: LICENSE
Requires-Dist: black ==23.7.0
Requires-Dist: click ==8.1.6
Requires-Dist: colorama ==0.4.6
Requires-Dist: mypy-extensions ==1.0.0
Requires-Dist: packaging ==23.1
Requires-Dist: pathspec ==0.11.2
Requires-Dist: platformdirs ==3.10.0
Requires-Dist: tomli ==2.0.1
Provides-Extra: discord
Requires-Dist: discord.py >=2.3.2 ; extra == 'discord'
